Metadata-Version: 2.4
Name: chibi_command
Version: 2.1.1
Summary: run terminal commands
Home-page: https://github.com/dem4ply/chibi_command
Author: Dem4ply
Author-email: dem4ply@gmail.com
License: WTFPL
Keywords: chibi_command
Classifier: Development Status :: 5 - Production/Stable
Classifier: Intended Audience :: Developers
Classifier: License :: Public Domain
Classifier: Natural Language :: English
Classifier: Natural Language :: Spanish
Classifier: Programming Language :: Python :: 3.7
Classifier: Programming Language :: Python :: 3.8
Classifier: Programming Language :: Python :: 3.9
Classifier: Programming Language :: Python :: 3.10
Classifier: Programming Language :: Python :: 3.11
Classifier: Programming Language :: Python :: 3.12
Classifier: Programming Language :: Python :: 3.13
Classifier: Programming Language :: Python :: 3.14
Classifier: Topic :: Utilities
License-File: LICENSE
License-File: AUTHORS.rst
Requires-Dist: chibi>=0.5.5
Requires-Dist: chibi_hybrid>=0.0.1
Requires-Dist: chibi-atlas>=1.1.0
Requires-Dist: chibi_requests>=1.2.0
Dynamic: author
Dynamic: author-email
Dynamic: classifier
Dynamic: description
Dynamic: home-page
Dynamic: keywords
Dynamic: license
Dynamic: license-file
Dynamic: requires-dist
Dynamic: summary
